odoo/addons/redis_session_store/__init__.py
odoo/addons/redis_session_store/__manifest__.py
odoo/addons/redis_session_store/env_config.py
odoo/addons/redis_session_store/json_encoding.py
odoo/addons/redis_session_store/odoo_monkey_patch.py
odoo/addons/redis_session_store/redis_session.py
odoo/addons/redis_session_store/environ_odoo_config/__init__.py
odoo/addons/redis_session_store/environ_odoo_config/auto_load.py
odoo/addons/redis_session_store/environ_odoo_config/mapper.py
mangono_addon_redis_session_store-2.2.0.dist-info/METADATA
mangono_addon_redis_session_store-2.2.0.dist-info/WHEEL
mangono_addon_redis_session_store-2.2.0.dist-info/entry_points.txt
mangono_addon_redis_session_store-2.2.0.dist-info/top_level.txt
mangono_addon_redis_session_store-2.2.0.dist-info/RECORD
