Metadata-Version: 2.4
Name: mangono-addon-redis_session_store
Version: 2.2.0
Project-URL: Homepage, http://mangono.fr/
Author-Email: mangono <opensource+odoo@mangono.fr>
License-Expression: AGPL-3.0
Classifier: Framework :: Odoo
Classifier: Framework :: Odoo :: 12.0
Classifier: Framework :: Odoo :: 13.0
Classifier: Framework :: Odoo :: 14.0
Classifier: Framework :: Odoo :: 15.0
Classifier: Framework :: Odoo :: 16.0
Classifier: Framework :: Odoo :: 17.0
Classifier: Framework :: Odoo :: 18.0
Classifier: Framework :: Odoo :: 19.0
Classifier: License :: OSI Approved :: GNU Affero General Public License v3
Classifier: Programming Language :: Python
Classifier: Programming Language :: Python :: 3
Classifier: Programming Language :: Python :: 3 :: Only
Classifier: Programming Language :: Python :: 3.10
Classifier: Programming Language :: Python :: 3.11
Classifier: Programming Language :: Python :: 3.12
Classifier: Programming Language :: Python :: 3.13
Classifier: Programming Language :: Python :: 3.8
Classifier: Programming Language :: Python :: 3.9
Requires-Dist: redis==5.2.1
Requires-Dist: environ-odoo-config<2,>=0.6.5
Requires-Dist: typing-extensions
Requires-Dist: wrapt==1.17.3
